cellcyclenet/__init__.py
cellcyclenet/_version.py
cellcyclenet/interface.py
cellcyclenet/unet2d.py
cellcyclenet/utils.py
cellcyclenet/models/__init__.py
cellcyclenet/models/pretrained-model_2D.pt
cellcyclenet/models/pretrained-model_3D.pt
cellcyclenet/unet3d/__init__.py
cellcyclenet/unet3d/buildingblocks.py
cellcyclenet/unet3d/config.py
cellcyclenet/unet3d/losses.py
cellcyclenet/unet3d/metrics.py
cellcyclenet/unet3d/model.py
cellcyclenet/unet3d/predictor.py
cellcyclenet/unet3d/se.py
cellcyclenet/unet3d/seg_metrics.py
cellcyclenet/unet3d/trainer.py
cellcyclenet/unet3d/utils.py
cellcyclenet-0.2.0.dist-info/LICENSE
cellcyclenet-0.2.0.dist-info/METADATA
cellcyclenet-0.2.0.dist-info/WHEEL
cellcyclenet-0.2.0.dist-info/top_level.txt
cellcyclenet-0.2.0.dist-info/RECORD
