Metadata-Version: 2.2
Name: cellcyclenet
Version: 0.2.0
Summary: Python package for predicting cell cycle stage from DAPI images
Home-page: https://github.com/Noble-Lab/CellCycleNet
License-File: LICENSE
Requires-Dist: matplotlib==3.9.1
Requires-Dist: numpy==2.0.1
Requires-Dist: pandas==2.2.2
Requires-Dist: scikit-image==0.24.0
Requires-Dist: scikit-learn==1.5.1
Requires-Dist: tifffile==2024.7.24
Requires-Dist: torch==2.3.1
Requires-Dist: torchaudio==2.3.1
Requires-Dist: torchvision==0.18.1
Dynamic: description
Dynamic: description-content-type
Dynamic: home-page
Dynamic: requires-dist
Dynamic: summary
